odoo8_addon_account_banking_sepa_credit_transfer-8.0.0.5.1.99.dev3-py3.8-nspkg.pth
odoo_addons/account_banking_sepa_credit_transfer/README.rst
odoo_addons/account_banking_sepa_credit_transfer/__init__.py
odoo_addons/account_banking_sepa_credit_transfer/__openerp__.py
odoo_addons/account_banking_sepa_credit_transfer/data/pain.001.001.02.xsd
odoo_addons/account_banking_sepa_credit_transfer/data/pain.001.001.03.xsd
odoo_addons/account_banking_sepa_credit_transfer/data/pain.001.001.04.xsd
odoo_addons/account_banking_sepa_credit_transfer/data/pain.001.001.05.xsd
odoo_addons/account_banking_sepa_credit_transfer/data/pain.001.003.03.xsd
odoo_addons/account_banking_sepa_credit_transfer/data/payment_type_sepa_sct.xml
odoo_addons/account_banking_sepa_credit_transfer/demo/sepa_credit_transfer_demo.xml
odoo_addons/account_banking_sepa_credit_transfer/i18n/account_banking_sepa_credit_transfer.pot
odoo_addons/account_banking_sepa_credit_transfer/i18n/am.po
odoo_addons/account_banking_sepa_credit_transfer/i18n/ar.po
odoo_addons/account_banking_sepa_credit_transfer/i18n/bg.po
odoo_addons/account_banking_sepa_credit_transfer/i18n/bs.po
odoo_addons/account_banking_sepa_credit_transfer/i18n/ca.po
odoo_addons/account_banking_sepa_credit_transfer/i18n/ca_ES.po
odoo_addons/account_banking_sepa_credit_transfer/i18n/cs.po
odoo_addons/account_banking_sepa_credit_transfer/i18n/da.po
odoo_addons/account_banking_sepa_credit_transfer/i18n/de.po
odoo_addons/account_banking_sepa_credit_transfer/i18n/el_GR.po
odoo_addons/account_banking_sepa_credit_transfer/i18n/en_AU.po
odoo_addons/account_banking_sepa_credit_transfer/i18n/en_GB.po
odoo_addons/account_banking_sepa_credit_transfer/i18n/es.po
odoo_addons/account_banking_sepa_credit_transfer/i18n/es_AR.po
odoo_addons/account_banking_sepa_credit_transfer/i18n/es_CL.po
odoo_addons/account_banking_sepa_credit_transfer/i18n/es_CO.po
odoo_addons/account_banking_sepa_credit_transfer/i18n/es_CR.po
odoo8_addon_account_banking_sepa_credit_transfer-8.0.0.5.1.99.dev3.dist-info/METADATA
odoo8_addon_account_banking_sepa_credit_transfer-8.0.0.5.1.99.dev3.dist-info/WHEEL
odoo8_addon_account_banking_sepa_credit_transfer-8.0.0.5.1.99.dev3.dist-info/namespace_packages.txt
odoo8_addon_account_banking_sepa_credit_transfer-8.0.0.5.1.99.dev3.dist-info/top_level.txt
odoo8_addon_account_banking_sepa_credit_transfer-8.0.0.5.1.99.dev3.dist-info/RECORD
